workbench/__init__.py
workbench/apps.py
django_workbench-0.1.1.dist-info/METADATA
django_workbench-0.1.1.dist-info/WHEEL
django_workbench-0.1.1.dist-info/licenses/LICENSE
django_workbench-0.1.1.dist-info/RECORD
